{
  "db_name": "PostgreSQL",
  "query": "\n        SELECT ops_name, name, tele_id\n        FROM usrs\n        WHERE is_valid = TRUE;\n        ",
  "describe": {
    "columns": [
      {
        "ordinal": 0,
        "name": "ops_name",
        "type_info": "Text"
      },
      {
        "ordinal": 1,
        "name": "name",
        "type_info": "Text"
      },
      {
        "ordinal": 2,
        "name": "tele_id",
        "type_info": "Int8"
      }
    ],
    "parameters": {
      "Left": []
    },
    "nullable": [
      false,
      false,
      false
    ]
  },
  "hash": "1cdf39c9224066b6195fff46bff2a6c2d3ff4116cddf98b8e48f964b1613e4b2"
}
